phonetic2bengali/__init__.py
phonetic2bengali/phonetic2bengalifunc.py
phonetic2bengali/pyavrophonetic/__init__.py
phonetic2bengali/pyavrophonetic/avro.py
phonetic2bengali/pyavrophonetic/config.py
phonetic2bengali/pyavrophonetic/resources/avrodict.json
phonetic2bengali/pyavrophonetic/utils/__init__.py
phonetic2bengali/pyavrophonetic/utils/count.py
phonetic2bengali/pyavrophonetic/utils/validate.py
phonetic2bengali-1.0.1.dist-info/METADATA
phonetic2bengali-1.0.1.dist-info/RECORD
phonetic2bengali-1.0.1.dist-info/WHEEL
phonetic2bengali-1.0.1.dist-info/top_level.txt
