Metadata-Version: 2.1
Name: phonetic2bengali
Version: 1.0.1
Summary: convert bengali text written in english to bengali while keeping english ony text
Home-page: https://github.org/SubrataSarkar32/phonetic2bengali/
Author: Subrata Sarkar
Author-email: subrotosarkar32@gmail.com
License: Apache v2.0
Platform: UNKNOWN
Classifier: Development Status :: 3 - Alpha
Classifier: Intended Audience :: Developers
Classifier: License :: OSI Approved :: Apache Software License
Classifier: Operating System :: OS Independent
Classifier: Programming Language :: Python :: 2.7
Classifier: Programming Language :: Python :: 3.6
Requires-Dist: simplejson (>=3.0.0)
Requires-Dist: pyenchant (>=2.0.0)
